MANIFEST.in
README.rst
setup.py
docs/HISTORY.txt
docs/LICENSE.GPL
docs/LICENSE.txt
ftw/__init__.py
ftw.zipextract.egg-info/PKG-INFO
ftw.zipextract.egg-info/SOURCES.txt
ftw.zipextract.egg-info/dependency_links.txt
ftw.zipextract.egg-info/entry_points.txt
ftw.zipextract.egg-info/namespace_packages.txt
ftw.zipextract.egg-info/not-zip-safe
ftw.zipextract.egg-info/requires.txt
ftw.zipextract.egg-info/top_level.txt
ftw/zipextract/__init__.py
ftw/zipextract/configure.zcml
ftw/zipextract/factory_type_decider.py
ftw/zipextract/file.py
ftw/zipextract/implementations_at.py
ftw/zipextract/implementations_dx.py
ftw/zipextract/interfaces.py
ftw/zipextract/testing.py
ftw/zipextract/zipextracter.py
ftw/zipextract/Extensions/__init__.py
ftw/zipextract/Extensions/install.py
ftw/zipextract/browser/__init__.py
ftw/zipextract/browser/configure.zcml
ftw/zipextract/browser/zipextract_view.py
ftw/zipextract/browser/resources/zipextract.css
ftw/zipextract/browser/resources/zipextract.js
ftw/zipextract/browser/templates/macros.pt
ftw/zipextract/browser/templates/zipextract.pt
ftw/zipextract/locales/ftw.zipextract.pot
ftw/zipextract/locales/de/LC_MESSAGES/ftw.zipextract.po
ftw/zipextract/locales/fr/LC_MESSAGES/ftw.zipextract.po
ftw/zipextract/profiles/default/cssregistry.xml
ftw/zipextract/profiles/default/jsregistry.xml
ftw/zipextract/profiles/default/metadata.xml
ftw/zipextract/profiles/uninstall/cssregistry.xml
ftw/zipextract/profiles/uninstall/jsregistry.xml
ftw/zipextract/tests/__init__.py
ftw/zipextract/tests/test_events.py
ftw/zipextract/tests/test_interfaces.py
ftw/zipextract/tests/test_profiles.py
ftw/zipextract/tests/test_uninstall.py
ftw/zipextract/tests/test_zipextract.py
ftw/zipextract/tests/assets/false_size.zip
ftw/zipextract/tests/assets/multi.zip
ftw/zipextract/tests/assets/name_conflict.zip
ftw/zipextract/tests/assets/outside.zip
ftw/zipextract/tests/assets/test.txt
ftw/zipextract/tests/assets/unicode.zip
ftw/zipextract/upgrades/__init__.py